{
  "notes": [
    {
      "id": "1",
      "category": "coding",
      "title": "Linux Tips",
      "noteBody": "The quick brown fox jump over the lazy dog near the side of the river bank"
    },
    {
      "id": "2",
      "category": "random",
      "title": "Personality Test",
      "noteBody": "The quick brown fox jump over the lazy dog near the side of the river bank"
    },
    {
      "id": "3",
      "category": "coding",
      "title": "Php Basics",
      "noteBody": "The quick brown fox jump over the lazy dog near the side of the river bank"
    },
    {
      "id": "4",
      "category": "random",
      "title": "My accounts",
      "noteBody": "The quick brown fox jump over the lazy dog near the side of the river bank"
    },
    {
      "id": "6",
      "category": "random",
      "title": "Debian tips",
      "noteBody": "The quick brown fox jump over the lazy dog near the side of the river bank"
    },
    {
      "id": "15df",
      "category": "random",
      "title": "Powershell for Begginers",
      "noteBody": "Learning powershell for begginers"
    },
    {
      "id": "d682",
      "category": "random",
      "title": "Basics of Bash Scripting",
      "noteBody": "This is the introduction into bash scripting in Linux environment"
    },
    {
      "id": "a419",
      "category": "random",
      "title": "Express JS with MongoDB",
      "noteBody": "This is a lessons for express js with mongodb"
    }
  ]
}